reactive_papi-2.0.0-py3.7-nspkg.pth
reactive/papi/Body.py
reactive/papi/FeedRequest.py
reactive/papi/FeedRequestAccept.py
reactive/papi/FeedRequestReject.py
reactive/papi/FeedType.py
reactive/papi/LiquidationOrder.py
reactive/papi/MDLevel2.py
reactive/papi/MDSnapshotL2.py
reactive/papi/Message.py
reactive/papi/PublicTrade.py
reactive/papi/SessionStatus.py
reactive/papi/Side.py
reactive/papi/SubReqType.py
reactive/papi/__init__.py
reactive_papi-2.0.0.dist-info/LICENSE
reactive_papi-2.0.0.dist-info/METADATA
reactive_papi-2.0.0.dist-info/WHEEL
reactive_papi-2.0.0.dist-info/namespace_packages.txt
reactive_papi-2.0.0.dist-info/top_level.txt
reactive_papi-2.0.0.dist-info/RECORD
